{
  "project_info": {
    "project_number": "1003563354480",
    "project_id": "dilo---incremental-game-e0b3e",
    "storage_bucket": "dilo---incremental-game-e0b3e.appspot.com"
  },
  "client": [
    {
      "client_info": {
        "mobilesdk_app_id": "1:1003563354480:android:9c2ac5e8e27280088ce7b5",
        "android_client_info": {
          "package_name": "com.dilo.invrementalgame"
        }
      },
      "oauth_client": [
        {
          "client_id": "1003563354480-gfsvc8i829p227tbasqjb60cu4ai165f.apps.googleusercontent.com",
          "client_type": 3
        }
      ],
      "api_key": [
        {
          "current_key": "AIzaSyAwWjc9kV3DRJEJJGBBdtrdvk85mIOa8P8"
        }
      ],
      "services": {
        "appinvite_service": {
          "other_platform_oauth_client": [
            {
              "client_id": "1003563354480-gfsvc8i829p227tbasqjb60cu4ai165f.apps.googleusercontent.com",
              "client_type": 3
            }
          ]
        }
      }
    }
  ],
  "configuration_version": "1"
}